setup.py
uranuspy/core.py
uranuspy/sdk.py
uranuspy/uranus_op.py
uranuspy/utils.py
uranuspy.egg-info/PKG-INFO
uranuspy.egg-info/SOURCES.txt
uranuspy.egg-info/dependency_links.txt
uranuspy.egg-info/requires.txt
uranuspy.egg-info/top_level.txt