Metadata-Version: 1.0
Name: uranuspy
Version: 0.2.6
Summary: 
Home-page: https://github.com/jinfagang/uranuspy
Author: Lucas Jin
Author-email: jinfagang19@163.com
License: GPL
Keywords: chatbot,wechat,message,telegram
Platform: any
